xarrayMannKendall/__init__.py
xarrayMannKendall/decorators.py
xarrayMannKendall/xarrayMannKendall.py
xarrayMannKendall-1.4.5.dist-info/LICENSE
xarrayMannKendall-1.4.5.dist-info/METADATA
xarrayMannKendall-1.4.5.dist-info/WHEEL
xarrayMannKendall-1.4.5.dist-info/top_level.txt
xarrayMannKendall-1.4.5.dist-info/RECORD
